copernicus_downloader/__init__.py
copernicus_downloader/config.py
copernicus_downloader/incremental.py
copernicus_downloader/logs.py
copernicus_downloader/main.py
copernicus_downloader/storage.py
copernicus_downloader/util.py
copernicus_downloader/post_processing/__init__.py
copernicus_downloader/post_processing/normalize_cams_solar_radiation.py
copernicus_downloader-1.2.1.dist-info/licenses/LICENSE
copernicus_downloader-1.2.1.dist-info/METADATA
copernicus_downloader-1.2.1.dist-info/WHEEL
copernicus_downloader-1.2.1.dist-info/entry_points.txt
copernicus_downloader-1.2.1.dist-info/top_level.txt
copernicus_downloader-1.2.1.dist-info/RECORD
