Metadata-Version: 2.4
Name: copernicus-downloader
Version: 1.2.1
Summary: An incremental downloader for Copernicus CDS / ADS datasets
Requires-Python: >=3.11
License-File: LICENSE
Requires-Dist: boto3>=1.40.21
Requires-Dist: cdsapi>=0.7.6
Requires-Dist: python-dotenv>=1.1.1
Requires-Dist: pyyaml>=6.0.2
Dynamic: license-file
